auto_anno_2/__init__.py
auto_anno_2/chatgpt-plugins.py
auto_anno_2/demo.py
auto_anno_2/local_config.py
auto_anno_2/server.py
auto_anno_2/test.py
auto_anno_2/utils/__init__.py
auto_anno_2/utils/anno/__init__.py
auto_anno_2/utils/anno/cls/__init__.py
auto_anno_2/utils/anno/cls/text_classification.py
auto_anno_2/utils/anno/cv/__init__.py
auto_anno_2/utils/anno/cv/openai_clip.py
auto_anno_2/utils/anno/cv/traditional.py
auto_anno_2/utils/anno/gen/__init__.py
auto_anno_2/utils/anno/gen/text_generate.py
auto_anno_2/utils/anno/ner/__init__.py
auto_anno_2/utils/anno/ner/entity_extract.py
auto_anno_2/utils/api/__init__.py
auto_anno_2/utils/api/aistudio_api.py
auto_anno_2/utils/api/chatglm_api.py
auto_anno_2/utils/api/chatglm_paddle.py
auto_anno_2/utils/api/google_trans.py
auto_anno_2/utils/api/openai_api.py
auto_anno_2/utils/api/xunfei_api.py
auto_anno_2/utils/api/yiyan_api.py
auto_anno_2/utils/api/zhipu_api.py
auto_anno_2/utils/format/__init__.py
auto_anno_2/utils/format/bio_2_json.py
auto_anno_2/utils/format/check_dataset.py
auto_anno_2/utils/format/get_rel_types.py
auto_anno_2/utils/format/other_2_cls.py
auto_anno_2/utils/format/other_2_ner.py
auto_anno_2/utils/format/txt_2_list.py
auto_anno_2/utils/format/wash.py
auto_anno_2-0.1.11.dist-info/METADATA
auto_anno_2-0.1.11.dist-info/WHEEL
auto_anno_2-0.1.11.dist-info/top_level.txt
auto_anno_2-0.1.11.dist-info/RECORD
