Metadata-Version: 2.1
Name: auto-anno-2
Version: 0.1.11
Summary: auto_anno_2
Home-page: https://github.com/LLMLab/auto_anno
Author: LLMLab
Author-email: 541182180@qq.com
License: UNKNOWN
Project-URL: Bug Tracker, https://github.com/LLMLab/auto_anno
Project-URL: Documentation, https://github.com/LLMLab/auto_anno
Project-URL: Source Code, https://github.com/LLMLab/auto_anno
Keywords: auto_anno_2
Platform: UNKNOWN
Classifier: Programming Language :: Python :: 3
Classifier: Operating System :: OS Independent
Requires-Dist: erniebot (==0.5.3)
